alu.v
`default_nettype none

// ALU de 8 bits - El corazón de tu CPU
module alu_8bit (
    input wire [7:0] a,          // Operando A
    input wire [7:0] b,          // Operando B
    input wire [2:0] op,         // Operación
    output reg [7:0] result,     // Resultado
    output wire zero,            // Flag: resultado es cero
    output wire carry,           // Flag: carry out
    output wire negative         // Flag: resultado negativo
);

    // Operaciones soportadas
    localparam OP_ADD  = 3'b000;
    localparam OP_SUB  = 3'b001;
    localparam OP_AND  = 3'b010;
    localparam OP_OR   = 3'b011;
    localparam OP_XOR  = 3'b100;
    localparam OP_SLL  = 3'b101;  // Shift Left Logical
    localparam OP_SRL  = 3'b110;  // Shift Right Logical
    localparam OP_SLT  = 3'b111;  // Set Less Than

    reg [8:0] result_extended;  // Para detectar carry
    
    always @(*) begin
        result_extended = 9'b0;
        case (op)
            OP_ADD: result_extended = {1'b0, a} + {1'b0, b};
            OP_SUB: result_extended = {1'b0, a} - {1'b0, b};
            OP_AND: result_extended = {1'b0, a & b};
            OP_OR:  result_extended = {1'b0, a | b};
            OP_XOR: result_extended = {1'b0, a ^ b};
            OP_SLL: result_extended = {1'b0, a << b[2:0]};
            OP_SRL: result_extended = {1'b0, a >> b[2:0]};
            OP_SLT: result_extended = {1'b0, (a < b) ? 8'h01 : 8'h00};
            default: result_extended = 9'b0;
        endcase
        
        result = result_extended[7:0];
    end
    
    // Flags
    assign zero = (result == 8'h00);
    assign carry = result_extended[8];
    assign negative = result[7];

endmodule

`default_nettype wire

tb_alu.v
`timescale 1ns/1ps

module tb_alu;
    reg [7:0] a, b;
    reg [2:0] op;
    wire [7:0] result;
    wire zero, carry, negative;
    
    // Instanciar ALU
    alu_8bit dut (
        .a(a),
        .b(b),
        .op(op),
        .result(result),
        .zero(zero),
        .carry(carry),
        .negative(negative)
    );
    
    // Nombres de operaciones para display
    reg [31:0] op_name;
    always @(*) begin
        case (op)
            3'b000: op_name = "ADD";
            3'b001: op_name = "SUB";
            3'b010: op_name = "AND";
            3'b011: op_name = "OR ";
            3'b100: op_name = "XOR";
            3'b101: op_name = "SLL";
            3'b110: op_name = "SRL";
            3'b111: op_name = "SLT";
            default: op_name = "???";
        endcase
    end
    
    // Test vectors
    integer errors = 0;
    
    task check_result;
        input [7:0] expected;
        input [31:0] test_name;
        begin
            #1;
            if (result !== expected) begin
                $display(" ERROR: %s", test_name);
                $display("   A=%d, B=%d, Op=%s", a, b, op_name);
                $display("   Expected: %d, Got: %d", expected, result);
                errors = errors + 1;
            end else begin
                $display(" PASS: %s (A=%d, B=%d, Result=%d)", 
                         op_name, a, b, result);
            end
        end
    endtask
    
    initial begin
        $dumpfile("sim/alu_waveform.vcd");
        $dumpvars(0, tb_alu);
        
        $display("\n╔════════════════════════════════════════╗");
        $display("║   MicroRV8-GT ALU Test Suite         ║");
        $display("║   Diseñado en Guatemala 🇬🇹            ║");
        $display("╚════════════════════════════════════════╝\n");
        
        // Test 1: Suma
        $display("─── Test 1: Adición ───");
        a = 8'd5; b = 8'd3; op = 3'b000;
        check_result(8'd8, "5 + 3 = 8");
        
        a = 8'd255; b = 8'd1; op = 3'b000;
        check_result(8'd0, "255 + 1 = 0 (overflow)");
        if (!carry) begin
            $display(" ERROR: Carry flag debería estar activo");
            errors = errors + 1;
        end
        
        // Test 2: Resta
        $display("\n─── Test 2: Sustracción ───");
        a = 8'd10; b = 8'd3; op = 3'b001;
        check_result(8'd7, "10 - 3 = 7");
        
        a = 8'd3; b = 8'd10; op = 3'b001;
        check_result(8'd249, "3 - 10 = -7 (249 en complemento a 2)");
        
        // Test 3: Operaciones lógicas
        $display("\n─── Test 3: Operaciones Lógicas ───");
        a = 8'b11110000; b = 8'b10101010; op = 3'b010;
        check_result(8'b10100000, "AND");
        
        a = 8'b11110000; b = 8'b10101010; op = 3'b011;
        check_result(8'b11111010, "OR");
        
        a = 8'b11110000; b = 8'b10101010; op = 3'b100;
        check_result(8'b01011010, "XOR");
        
        // Test 4: Shifts
        $display("\n─── Test 4: Desplazamientos ───");
        a = 8'b00000011; b = 8'd2; op = 3'b101;
        check_result(8'b00001100, "3 << 2 = 12");
        
        a = 8'b11000000; b = 8'd2; op = 3'b110;
        check_result(8'b00110000, "192 >> 2 = 48");
        
        // Test 5: Comparación
        $display("\n─── Test 5: Comparación (SLT) ───");
        a = 8'd5; b = 8'd10; op = 3'b111;
        check_result(8'd1, "5 < 10 = TRUE");
        
        a = 8'd10; b = 8'd5; op = 3'b111;
        check_result(8'd0, "10 < 5 = FALSE");
        
        // Test 6: Flag Zero
        $display("\n─── Test 6: Zero Flag ───");
        a = 8'd5; b = 8'd5; op = 3'b001;
        #1;
        if (zero)
            $display(" PASS: Zero flag activo (5 - 5 = 0)");
        else begin
            $display(" ERROR: Zero flag debería estar activo");
            errors = errors + 1;
        end
        
        // Resumen
        $display("\n╔════════════════════════════════════════╗");
        if (errors == 0) begin
            $display("║    TODOS LOS TESTS PASARON       ║");
            $display("║   Tu ALU funciona perfectamente       ║");
        end else begin
            $display("║     %0d ERRORES ENCONTRADOS          ║", errors);
            $display("║   Revisa el código y reintenta        ║");
        end
        $display("╚════════════════════════════════════════╝\n");
        
        $finish;
    end

endmodule

sim/alu_waveform.vcd
$date
	Mon Feb 16 20:18:53 2026
$end
$version
	Icarus Verilog
$end
$timescale
	1ps
$end
$scope module tb_alu $end
$var wire 1 ! zero $end
$var wire 8 " result [7:0] $end
$var wire 1 # negative $end
$var wire 1 $ carry $end
$var reg 8 % a [7:0] $end
$var reg 8 & b [7:0] $end
$var reg 3 ' op [2:0] $end
$var reg 32 ( op_name [31:0] $end
$var integer 32 ) errors [31:0] $end
$scope module dut $end
$var wire 8 * a [7:0] $end
$var wire 8 + b [7:0] $end
$var wire 3 , op [2:0] $end
$var wire 1 ! zero $end
$var wire 1 # negative $end
$var wire 1 $ carry $end
$var reg 8 - result [7:0] $end
$var reg 9 . result_extended [8:0] $end
$upscope $end
$scope task check_result $end
$var reg 8 / expected [7:0] $end
$var reg 32 0 test_name [31:0] $end
$upscope $end
$upscope $end
$enddefinitions $end
#0
$dumpvars
b100000001111010010000000111000 0
b1000 /
b1000 .
b1000 -
b0 ,
b11 +
b101 *
b0 )
b10000010100010001000100 (
b0 '
b11 &
b101 %
0$
0#
b1000 "
0!
$end
#1000
1$
1!
b0 "
b0 -
b100000000 .
b1101100011011110111011100101001 0
b0 /
b1 &
b1 +
b11111111 %
b11111111 *
#2000
0$
b10100110101010101000010 (
0!
b111 "
b111 -
b111 .
b100000001111010010000000110111 0
b111 /
b1 '
b1 ,
b11 &
b11 +
b1010 %
b1010 *
#3000
1#
1$
b11111001 "
b11111001 -
b111111001 .
b1100001001000000011001000101001 0
b11111001 /
b1010 &
b1010 +
b11 %
b11 *
#4000
0$
b10000010100111001000100 (
b10100000 "
b10100000 -
b10100000 .
b10000010100111001000100 0
b10100000 /
b10 '
b10 ,
b10101010 &
b10101010 +
b11110000 %
b11110000 *
#5000
b11111010 "
b11111010 -
b11111010 .
b10011110101001000100000 (
b100111101010010 0
b11111010 /
b11 '
b11 ,
#6000
0#
b1011010 "
b1011010 -
b1011010 .
b10110000100111101010010 (
b10110000100111101010010 0
b1011010 /
b100 '
b100 ,
#7000
b10100110100110001001100 (
b1100 "
b1100 -
b1100 .
b111101001000000011000100110010 0
b1100 /
b101 '
b101 ,
b10 &
b10 +
b11 %
b11 *
#8000
b10100110101001001001100 (
b110000 "
b110000 -
b110000 .
b111101001000000011010000111000 0
b110000 /
b110 '
b110 ,
b11000000 %
b11000000 *
#9000
b10100110100110001010100 (
b1 "
b1 -
b1 .
b1010100010100100101010101000101 0
b1 /
b111 '
b111 ,
b1010 &
b1010 +
b101 %
b101 *
#10000
1!
b0 "
b0 -
b0 .
b1000001010011000101001101000101 0
b0 /
b101 &
b101 +
b1010 %
b1010 *
#11000
b10100110101010101000010 (
b1 '
b1 ,
b101 %
b101 *
