regfile.v
`default_nettype none

// Banco de registros: 8 registros x 8 bits
// Arquitectura RISC-V style: r0 siempre es 0
module regfile (
    input wire clk,
    input wire rst_n,
    
    // Puerto de lectura 1
    input wire [2:0] rs1_addr,
    output wire [7:0] rs1_data,
    
    // Puerto de lectura 2
    input wire [2:0] rs2_addr,
    output wire [7:0] rs2_data,
    
    // Puerto de escritura
    input wire [2:0] rd_addr,
    input wire [7:0] rd_data,
    input wire rd_we            // Write enable
);

    // 8 registros de 8 bits
    reg [7:0] registers [0:7];
    
    // Lecturas son combinacionales
    assign rs1_data = (rs1_addr == 3'b000) ? 8'h00 : registers[rs1_addr];
    assign rs2_data = (rs2_addr == 3'b000) ? 8'h00 : registers[rs2_addr];
    
    // Escritura es síncrona
    always @(posedge clk or negedge rst_n) begin
        if (!rst_n) begin
            // Reset: todos los registros a 0
            registers[0] <= 8'h00;
            registers[1] <= 8'h00;
            registers[2] <= 8'h00;
            registers[3] <= 8'h00;
            registers[4] <= 8'h00;
            registers[5] <= 8'h00;
            registers[6] <= 8'h00;
            registers[7] <= 8'h00;
        end else if (rd_we && rd_addr != 3'b000) begin
            // r0 nunca se escribe (siempre 0 en RISC-V)
            registers[rd_addr] <= rd_data;
        end
    end

endmodule

`default_nettype wire

tb_regfile.v
`timescale 1ns/1ps

module tb_regfile;
    reg clk;
    reg rst_n;
    reg [2:0] rs1_addr, rs2_addr, rd_addr;
    wire [7:0] rs1_data, rs2_data;
    reg [7:0] rd_data;
    reg rd_we;
    
    // Instanciar DUT
    regfile dut (
        .clk(clk),
        .rst_n(rst_n),
        .rs1_addr(rs1_addr),
        .rs1_data(rs1_data),
        .rs2_addr(rs2_addr),
        .rs2_data(rs2_data),
        .rd_addr(rd_addr),
        .rd_data(rd_data),
        .rd_we(rd_we)
    );
    
    // Clock generation
    initial clk = 0;
    always #5 clk = ~clk;
    
    initial begin
        $dumpfile("sim/regfile_waveform.vcd");
        $dumpvars(0, tb_regfile);
        
        $display("\n╔════════════════════════════════════════╗");
        $display("║   Register File Test Suite            ║");
        $display("╚════════════════════════════════════════╝\n");
        
        // Reset
        rst_n = 0;
        rd_we = 0;
        #20 rst_n = 1;
        
        // Test 1: Escribir en registros
        $display("─── Test 1: Escritura ───");
        @(posedge clk);
        rd_addr = 3'd1; rd_data = 8'hAA; rd_we = 1;
        @(posedge clk);
        rd_addr = 3'd2; rd_data = 8'hBB; rd_we = 1;
        @(posedge clk);
        rd_addr = 3'd3; rd_data = 8'hCC; rd_we = 1;
        @(posedge clk);
        rd_we = 0;
        
        // Test 2: Leer registros
        $display("─── Test 2: Lectura ───");
        rs1_addr = 3'd1; rs2_addr = 3'd2;
        #1;
        $display("r1 = 0x%02h (esperado: 0xAA)", rs1_data);
        $display("r2 = 0x%02h (esperado: 0xBB)", rs2_data);
        
        // Test 3: r0 siempre es 0
        $display("\n─── Test 3: r0 inmutable ───");
        @(posedge clk);
        rd_addr = 3'd0; rd_data = 8'hFF; rd_we = 1;
        @(posedge clk);
        rd_we = 0;
        rs1_addr = 3'd0;
        #1;
        if (rs1_data == 8'h00)
            $display(" PASS: r0 permanece en 0");
        else
            $display(" ERROR: r0 = 0x%02h (debería ser 0x00)", rs1_data);
        
        #50;
        $display("\n Tests completos\n");
        $finish;
    end

endmodule

sim/regfile_waveform.vcd
$date
	Mon Feb 16 20:13:19 2026
$end
$version
	Icarus Verilog
$end
$timescale
	1ps
$end
$scope module tb_regfile $end
$var wire 8 ! rs2_data [7:0] $end
$var wire 8 " rs1_data [7:0] $end
$var reg 1 # clk $end
$var reg 3 $ rd_addr [2:0] $end
$var reg 8 % rd_data [7:0] $end
$var reg 1 & rd_we $end
$var reg 3 ' rs1_addr [2:0] $end
$var reg 3 ( rs2_addr [2:0] $end
$var reg 1 ) rst_n $end
$scope module dut $end
$var wire 1 # clk $end
$var wire 3 * rd_addr [2:0] $end
$var wire 8 + rd_data [7:0] $end
$var wire 1 & rd_we $end
$var wire 3 , rs1_addr [2:0] $end
$var wire 3 - rs2_addr [2:0] $end
$var wire 1 ) rst_n $end
$var wire 8 . rs2_data [7:0] $end
$var wire 8 / rs1_data [7:0] $end
$upscope $end
$upscope $end
$enddefinitions $end
#0
$dumpvars
bx /
bx .
bx -
bx ,
bx +
bx *
0)
bx (
bx '
0&
bx %
bx $
0#
bx "
bx !
$end
#5000
1#
#10000
0#
#15000
1#
#20000
0#
1)
#25000
1&
b10101010 %
b10101010 +
b1 $
b1 *
1#
#30000
0#
#35000
b10111011 %
b10111011 +
b10 $
b10 *
1#
#40000
0#
#45000
b11001100 %
b11001100 +
b11 $
b11 *
1#
#50000
0#
#55000
b10111011 !
b10111011 .
b10101010 "
b10101010 /
b10 (
b10 -
b1 '
b1 ,
0&
1#
#60000
0#
#65000
1&
b11111111 %
b11111111 +
b0 $
b0 *
1#
#70000
0#
#75000
b0 "
b0 /
b0 '
b0 ,
0&
1#
